ad_sdl_wei-0.7.4.dist-info/licenses/LICENSE
wei/__init__.py
wei/config.py
wei/engine.py
wei/experiment_client.py
wei/server.py
wei/utils.py
wei/core/__init__.py
wei/core/admin.py
wei/core/events.py
wei/core/experiment.py
wei/core/location.py
wei/core/loggers.py
wei/core/module.py
wei/core/notifications.py
wei/core/scheduler.py
wei/core/state_manager.py
wei/core/step.py
wei/core/storage.py
wei/core/workcell.py
wei/core/workflow.py
wei/core/workflow_admin.py
wei/core/interfaces/__init__.py
wei/core/interfaces/rest_interface.py
wei/core/interfaces/ros2_interface.py
wei/core/interfaces/simulate_interface.py
wei/core/interfaces/tcp_interface.py
wei/core/interfaces/zmq_interface.py
wei/modules/__init__.py
wei/modules/rest_module.py
wei/modules/utility_module.py
wei/routers/__init__.py
wei/routers/admin_routes.py
wei/routers/campaign_routes.py
wei/routers/data_routes.py
wei/routers/event_routes.py
wei/routers/experiment_routes.py
wei/routers/location_routes.py
wei/routers/module_routes.py
wei/routers/workcell_routes.py
wei/routers/workflow_routes.py
wei/types/__init__.py
wei/types/base_types.py
wei/types/datapoint_types.py
wei/types/event_types.py
wei/types/exceptions.py
wei/types/experiment_types.py
wei/types/interface_types.py
wei/types/module_types.py
wei/types/step_types.py
wei/types/workcell_types.py
wei/types/workflow_types.py
ad_sdl_wei-0.7.4.dist-info/METADATA
ad_sdl_wei-0.7.4.dist-info/WHEEL
ad_sdl_wei-0.7.4.dist-info/top_level.txt
ad_sdl_wei-0.7.4.dist-info/RECORD
