Metadata-Version: 2.4
Name: ad_sdl.wei
Version: 0.7.4
Summary: The Rapid Prototyping Laboratory's Workflow Execution Interface.
Author-email: Rafael Vescovi <ravescovi@anl.gov>, Tobias Ginsburg <tginsburg@anl.gov>, "Ryan D. Lewis" <ryan.lewis@anl.gov>, Casey Stone <cstone@anl.gov>, Doga Ozgulbas <dozgulbas@anl.gov>, Kyle Hippe <khippe@anl.gov>
License: MIT
Project-URL: Homepage, https://github.com/AD-SDL/wei
Project-URL: Downloads, https://github.com/AD-SDL/wei/archive/refs/tags/0.5.1.tar.gz
Requires-Python: >=3.9.1
License-File: LICENSE
Requires-Dist: devtools>=0.12
Requires-Dist: fastapi>=0.110
Requires-Dist: pottery>=3.0.0
Requires-Dist: pydantic>=2.4
Requires-Dist: python-multipart>=0.0.6
Requires-Dist: PyYAML>=6.0
Requires-Dist: redis>=4.2.2
Requires-Dist: requests>=2.31.0
Requires-Dist: uvicorn[standard]>=0.21
Requires-Dist: websockets>=12.0
Requires-Dist: secure-smtplib>=0.1.1
Requires-Dist: aenum>=3.1.15
Requires-Dist: colorama>=0.4.6
Requires-Dist: pause>=0.3
Requires-Dist: pydantic-extra-types>=2.9.0
Requires-Dist: python-ulid[pydantic]>=2.7.0
Requires-Dist: rich>=13.9.2
Provides-Extra: dev
Requires-Dist: build; extra == "dev"
Requires-Dist: mypy; extra == "dev"
Requires-Dist: pre-commit>=4.0.1; extra == "dev"
Requires-Dist: pytest>=7.4.4; extra == "dev"
Requires-Dist: ruff; extra == "dev"
Requires-Dist: types-aiofiles; extra == "dev"
Requires-Dist: types-jwt; extra == "dev"
Requires-Dist: types-orjson; extra == "dev"
Requires-Dist: types-python-dateutil; extra == "dev"
Requires-Dist: types-PyYAML; extra == "dev"
Requires-Dist: types-redis; extra == "dev"
Requires-Dist: types-requests; extra == "dev"
Requires-Dist: types-ujson; extra == "dev"
Provides-Extra: docs
Requires-Dist: autodoc-pydantic; extra == "docs"
Requires-Dist: sphinx; extra == "docs"
Requires-Dist: sphinx-rtd-theme; extra == "docs"
Provides-Extra: zmq
Requires-Dist: pyzmq>=25.1.1; extra == "zmq"
Provides-Extra: diaspora
Requires-Dist: urllib3<2; extra == "diaspora"
Requires-Dist: diaspora_event_sdk[kafka-python]>=0.1.2; extra == "diaspora"
Dynamic: license-file
